fnos/__init__.py
fnos/client.py
fnos/exceptions.py
fnos/file.py
fnos/network.py
fnos/resource_monitor.py
fnos/sac.py
fnos/store.py
fnos/system_info.py
fnos/user.py
fnos-0.10.1.dist-info/licenses/LICENSE
fnos-0.10.1.dist-info/METADATA
fnos-0.10.1.dist-info/WHEEL
fnos-0.10.1.dist-info/top_level.txt
fnos-0.10.1.dist-info/RECORD
