Metadata-Version: 2.4
Name: fnos
Version: 0.10.1
Summary: 飞牛fnOS的Python SDK。
Project-URL: Homepage, https://github.com/Timandes/pyfnos
Project-URL: Repository, https://github.com/Timandes/pyfnos.git
Requires-Python: >=3.11
License-File: LICENSE
Requires-Dist: websockets>=15.0
Requires-Dist: pycryptodome>=3.23.0
Dynamic: license-file
